vultus_serpentis/__init__.py
vultus_serpentis/actions.py
vultus_serpentis/commands.py
vultus_serpentis/common.py
vultus_serpentis/events.py
vultus_serpentis/setup.py
vultus_serpentis/validation.py
vultus_serpentis-0.1.0.dist-info/METADATA
vultus_serpentis-0.1.0.dist-info/WHEEL
vultus_serpentis-0.1.0.dist-info/top_level.txt
vultus_serpentis-0.1.0.dist-info/RECORD
