Metadata-Version: 2.1
Name: vultus-serpentis
Version: 0.1.0
Summary: Modern Tkinter utilities for TTK and TTKBootstrap applications
Home-page: https://github.com/yourusername/vultus-serpentis
Author: Vultus Serpentis Contributors
License: MIT
Project-URL: Homepage, https://github.com/yourusername/vultus-serpentis
Project-URL: Documentation, https://github.com/yourusername/vultus-serpentis/blob/main/README.md
Project-URL: Repository, https://github.com/yourusername/vultus-serpentis
Keywords: gui framework observable event-bus commands validation actions tkinter mvc
Classifier: Development Status :: 3 - Alpha
Classifier: Intended Audience :: Developers
Classifier: License :: OSI Approved :: MIT License
Classifier: Programming Language :: Python :: 3
Classifier: Programming Language :: Python :: 3.9
Classifier: Programming Language :: Python :: 3.10
Classifier: Programming Language :: Python :: 3.11
Classifier: Programming Language :: Python :: 3.12
Classifier: Topic :: Software Development :: Libraries :: Python Modules
Classifier: Topic :: Software Development :: User Interfaces
Requires-Python: >=3.9
Requires-Dist: tkinter-tooltip (>=3.0.0)
Provides-Extra: bootstrap
Requires-Dist: ttkbootstrap (>=1.10.0) ; extra == 'bootstrap'
Provides-Extra: dev
Requires-Dist: pytest (>=7.0.0) ; extra == 'dev'
Requires-Dist: pytest-cov (>=4.0.0) ; extra == 'dev'
Requires-Dist: mypy (>=1.0.0) ; extra == 'dev'
Requires-Dist: pylint (>=2.15.0) ; extra == 'dev'
